note_template/__init__.py
note_template/cli.py
note_template-0.3.1.dist-info/entry_points.txt
note_template-0.3.1.dist-info/WHEEL
note_template-0.3.1.dist-info/METADATA
note_template-0.3.1.dist-info/RECORD
